fourier_drawing/__init__.py
fourier_drawing/abstract.py
fourier_drawing/colors.py
fourier_drawing/context.py
fourier_drawing/curves.py
fourier_drawing/draw.py
fourier_drawing/fourier.py
fourier_drawing/interpolation.py
fourier_drawing/manager.py
fourier_drawing/movinginterpolation.py
fourier_drawing/plane.py
fourier_drawing/polynomial.py
fourier_drawing/rect.py
fourier_drawing/tools.py
fourier_drawing/window.py
fourier_drawing-0.1.8.dist-info/LICENSE
fourier_drawing-0.1.8.dist-info/METADATA
fourier_drawing-0.1.8.dist-info/WHEEL
fourier_drawing-0.1.8.dist-info/RECORD
