Metadata-Version: 2.1
Name: fourier-drawing
Version: 0.1.8
Summary: 
Home-page: https://github.com/marcpartensky/fourier
Author: Marc Partensky
Author-email: marc.partensky@gmail.com
Requires-Python: >=3.10,<4.0
Classifier: Programming Language :: Python :: 3
Classifier: Programming Language :: Python :: 3.10
Classifier: Programming Language :: Python :: 3.11
Requires-Dist: numpy (>=1.22.4,<2.0.0)
Requires-Dist: opencv-python (>=4.5.5,<5.0.0)
Requires-Dist: pygame (>=2.1.2,<3.0.0)
Project-URL: Repository, https://github.com/marcpartensky/fourier
